nilspodlib/__init__.py
nilspodlib/_session_base.py
nilspodlib/calibration_utils.py
nilspodlib/consts.py
nilspodlib/dataset.py
nilspodlib/datastream.py
nilspodlib/exceptions.py
nilspodlib/header.py
nilspodlib/legacy.py
nilspodlib/session.py
nilspodlib/utils.py
nilspodlib-4.1.1.dist-info/METADATA
nilspodlib-4.1.1.dist-info/WHEEL
nilspodlib-4.1.1.dist-info/licenses/LICENSE
nilspodlib-4.1.1.dist-info/RECORD
