Metadata-Version: 2.4
Name: nilspodlib
Version: 4.1.1
Summary: A Python library to load and convert sensor data recorded by a NilsPod by Portablies.
Project-URL: Homepage, https://github.com/mad-lab-fau/NilsPodLib
Project-URL: Repository, https://github.com/mad-lab-fau/NilsPodLib
Project-URL: Documentation, https://nilspodlib.readthedocs.io/en/latest/
Author-email: Arne Küderle <arne.kuederle@fau.de>, Nils Roth <nils.roth@fau.de>, Robert Richer <robert.richer@fau.de>
License-Expression: MIT
License-File: LICENSE
Keywords: IMU,accelerometer,scientific,sensors
Classifier: Intended Audience :: Science/Research
Classifier: Topic :: Scientific/Engineering
Classifier: Topic :: Scientific/Engineering :: Physics
Requires-Python: <4.0,>=3.9
Requires-Dist: imucal>=2.0.0
Requires-Dist: numpy>=1.23.2
Requires-Dist: pandas>=1.1.3
Requires-Dist: scipy>=1.5.2
Requires-Dist: typing-extensions>=4.3.0
